gnosisai/README.md
gnosisai/__init__.py
gnosisai/builder.py
gnosisai/correspond_file_path.yaml
gnosisai/main.py
gnosisai/requirements.txt
gnosisai/vars.yaml
gnosisai/template/.gitignore
gnosisai/template/README.md
gnosisai/template/VERSION
gnosisai/template/__init__.py
gnosisai/template/docker_build.sh
gnosisai/template/requirements.txt
gnosisai/template/run.sh
gnosisai/template/manifests/.gitkeep
gnosisai/template/models/.gitkeep
gnosisai/template/src/__init__.py
gnosisai/template/src/configurations.py
gnosisai/template/src/constants.py
gnosisai/template/src/app/__init__.py
gnosisai/template/src/app/app.py
gnosisai/template/src/app/routers/__init__.py
gnosisai/template/src/ml/__init__.py
gnosisai/template/src/services/__init__.py
gnosisai/template/src/utils/__init__.py
gnosisai/template/src/utils/logging.conf
gnosisai/template/src/utils/profiler.py
gnosisai/template_files/Dockerfile.j2
gnosisai/template_files/deployment.yml.j2
gnosisai/template_files/docker-compose.yml.j2
gnosisai/template_files/logger.py.j2
gnosisai/template_files/makefile.j2
gnosisai/template_files/namespace.yml.j2
gnosisai/template_files/prediction.py.j2
gnosisai/template_files/routers.py.j2
gnosisai-0.4.dist-info/METADATA
gnosisai-0.4.dist-info/WHEEL
gnosisai-0.4.dist-info/entry_points.txt
gnosisai-0.4.dist-info/top_level.txt
gnosisai-0.4.dist-info/RECORD
