Metadata-Version: 2.1
Name: gnosisai
Version: 0.4
Requires-Dist: jinja2
Requires-Dist: click
Requires-Dist: PyYAML
